{
  "type": "minecraft:crafting_shaped",
  "pattern": [
    "PDP",
    "WMW",
    "GBG"
  ],
  "key": {
    "P": {
      "item": "create:mechanical_press"
    },
    "D": {
      "item": "techpack:polished_diamond"
    },
    "W": {
      "item": "createaddition:copper_spool"
    },
    "M": {
      "item": "techpack:basic_machine_casing"
    },
    "G": {
      "tag": "c:gears/steel"
    },
    "B": {
      "item": "techpack:basic_circuit"
    }
  },
  "result": {
    "id": "techpack:basic_compressor"
  }
}